LICENSE.txt
MANIFEST.in
README.md
pyproject.toml
setup.cfg
setup.py
moose_frank/__init__.py
moose_frank.egg-info/PKG-INFO
moose_frank.egg-info/SOURCES.txt
moose_frank.egg-info/dependency_links.txt
moose_frank.egg-info/not-zip-safe
moose_frank.egg-info/requires.txt
moose_frank.egg-info/top_level.txt
moose_frank/graphene/__init__.py
moose_frank/graphene/conf.py
moose_frank/graphene/converter.py
moose_frank/graphene/mutations.py
moose_frank/graphene/schema_mixins.py
moose_frank/graphene/types.py
moose_frank/graphene/utils.py
moose_frank/locale/nl/LC_MESSAGES/django.mo
moose_frank/locale/nl/LC_MESSAGES/django.po
moose_frank/management/__init__.py
moose_frank/management/commands/__init__.py
moose_frank/management/commands/generate_urlpatterns.py
moose_frank/storages/__init__.py
moose_frank/storages/gcloud.py
moose_frank/templatetags/__init__.py
moose_frank/templatetags/active.py
moose_frank/templatetags/generic.py
moose_frank/templatetags/mathtags.py
moose_frank/tests/__init__.py
moose_frank/tests/django.py
moose_frank/tests/graphql.py
moose_frank/tests/pillow.py
moose_frank/tests/requests_mock.py
moose_frank/utils/__init__.py
moose_frank/utils/cache.py
moose_frank/utils/dates.py
moose_frank/utils/filters.py
moose_frank/utils/network.py
moose_frank/utils/sanitizer.py
moose_frank/utils/text.py
moose_frank/utils/validators.py