Metadata-Version: 2.1
Name: moose-frank
Version: 10.0.1
Summary: A Python package packed with tools that are commonly used in Moose projects.
Home-page: https://gitlab.com/mediamoose/moose-frank/tree/v10.0.1
Download-URL: https://gitlab.com/mediamoose/moose-frank/repository/v10.0.1/archive.tar.gz
Author: Sven Groot (Moose / Digital Agency)
Author-email: sven@wearemoose.com
License: MIT
Keywords: moose,frank,frankenstein
Classifier: Development Status :: 3 - Alpha
Classifier: Framework :: Django
Classifier: Framework :: Django :: 3.2
Classifier: Framework :: Django :: 4.2
Classifier: Intended Audience :: Developers
Classifier: License :: OSI Approved :: MIT License
Classifier: Natural Language :: English
Classifier: Operating System :: POSIX :: Linux
Classifier: Programming Language :: Python
Classifier: Programming Language :: Python :: 3.8
Classifier: Programming Language :: Python :: 3.9
Classifier: Programming Language :: Python :: 3.10
Classifier: Programming Language :: Python :: 3.11
Classifier: Programming Language :: Python :: 3.12
Requires-Python: >=3.8
Provides-Extra: graphene
Provides-Extra: gcloud
License-File: LICENSE.txt
